sqlalchemy_metajson/__init__.py
sqlalchemy_metajson/get_type.py
sqlalchemy_metajson/metajson.py
SQLAlchemy_MetaJSON-1.0.6.dist-info/LICENSE.rst
SQLAlchemy_MetaJSON-1.0.6.dist-info/METADATA
SQLAlchemy_MetaJSON-1.0.6.dist-info/WHEEL
SQLAlchemy_MetaJSON-1.0.6.dist-info/top_level.txt
SQLAlchemy_MetaJSON-1.0.6.dist-info/RECORD
